djx_account/.git
djx_account/.gitignore
djx_account/__init__.py
djx_account/admin.py
djx_account/apps.py
djx_account/email_constructor.py
djx_account/management/__init__.py
djx_account/management/commands/__init__.py
djx_account/management/commands/create_admin.py
djx_account/managers.py
djx_account/migrations/0001_initial.py
djx_account/migrations/0002_alter_oauthcredentials_access_token_and_more.py
djx_account/migrations/0003_user_birth_date_user_phone_number.py
djx_account/migrations/0004_user_country.py
djx_account/migrations/0005_user_gender.py
djx_account/migrations/__init__.py
djx_account/models.py
djx_account/serializers/__init__.py
djx_account/serializers/base_oauth_serializers.py
djx_account/serializers/dj_rest_auth_serializers.py
djx_account/serializers/login_serializers.py
djx_account/serializers/oauth_credentials_serializers.py
djx_account/serializers/registration_serializers.py
djx_account/serializers/reset_password_serializers.py
djx_account/serializers/user_claims_serializer.py
djx_account/serializers/user_confirmation_serializers.py
djx_account/serializers/user_serializers.py
djx_account/serializers/user_token_serializers.py
djx_account/services/__init__.py
djx_account/services/discord_service.py
djx_account/services/facebook_service.py
djx_account/services/google_service.py
djx_account/services/microsoft_service.py
djx_account/services/oauth_service_interface.py
djx_account/services/twitter_service.py
djx_account/settings.py
djx_account/signals/__init__.py
djx_account/signals/receivers.py
djx_account/signals/senders.py
djx_account/templates/header/mail.html
djx_account/templates/password_reset/mail.html
djx_account/templates/registration_welcome/mail.html
djx_account/templates/user_confirmation/mail.html
djx_account/tests/__init__.py
djx_account/tests/tests_login_serializer.py
djx_account/tests/tests_login_view.py
djx_account/tests/tests_registation_serializer.py
djx_account/tests/tests_registration_view.py
djx_account-0.3.3.dist-info/METADATA
djx_account-0.3.3.dist-info/WHEEL
djx_account-0.3.3.dist-info/RECORD
