Metadata-Version: 2.1
Name: djx-account
Version: 0.3.3
Summary: 
Author: nope
Requires-Python: >=3.10,<4.0
Classifier: Programming Language :: Python :: 3
Classifier: Programming Language :: Python :: 3.10
Classifier: Programming Language :: Python :: 3.11
Requires-Dist: django (>=4.1.4,<6.0)
Requires-Dist: djangorestframework (>=3.14.0,<4.0.0)
Requires-Dist: djangorestframework-simplejwt (>=5.2.2,<6.0.0)
Requires-Dist: facebook-sdk (>=3.1.0,<4.0.0)
Requires-Dist: google-auth (>=2.15.0,<3.0.0)
Requires-Dist: jinja2 (>=3.1.2,<4.0.0)
Requires-Dist: msal (>=1.20.0,<2.0.0)
Requires-Dist: requests (>=2.28.1,<3.0.0)
Requires-Dist: tweepy (>=4.12.1,<5.0.0)
